[{"vacancy": "Lead QA engineer", "min_salary": "270000", "max_salary": null, "currency": "\u0440\u0443\u0431", "company": "\u041c\u0435\u0442\u0440 \u041a\u0432\u0430\u0434\u0440\u0430\u0442\u043d\u044b\u0439", "city": "\u041c\u043e\u0441\u043a\u0432\u0430", "link": "https://hh.ru/vacancy/45469247?query=qa%20automation%20lead", "site": "https://hh.ru/search/vacancy"}, {"vacancy": "Senior QA Automation Engineer (Python)", "min_salary": "300000", "max_salary": null, "currency": "\u0440\u0443\u0431", "company": "Scalable Solutions", "city": "\u041c\u043e\u0441\u043a\u0432\u0430", "link": "https://hh.ru/vacancy/45114743?query=qa%20automation%20lead", "site": "https://hh.ru/search/vacancy"}, {"vacancy": "Senior/Lead QA Automation Engineer", "min_salary": "250000", "max_salary": "350000", "currency": "\u0440\u0443\u0431", "company": "Scalable Solutions", "city": "\u041c\u043e\u0441\u043a\u0432\u0430", "link": "https://hh.ru/vacancy/44922362?query=qa%20automation%20lead", "site": "https://hh.ru/search/vacancy"}, {"vacancy": "Senior QA Automation engineer/SDET", "min_salary": "4000", "max_salary": "5500", "currency": "USD", "company": "\u041e\u041e\u041e \u041e\u043d\u0422\u0430\u0440\u0433\u0435\u0442 \u041b\u0410\u0411\u0421", "city": "\u041c\u043e\u0441\u043a\u0432\u0430", "link": "https://hh.ru/vacancy/45568683?query=qa%20automation%20lead", "site": "https://hh.ru/search/vacancy"}, {"vacancy": "Senior QA Engineer (Automation)", "min_salary": "200000", "max_salary": "300000", "currency": "\u0440\u0443\u0431", "company": "\u0412\u0430\u043b\u0430\u0440\u043c", "city": "\u041c\u043e\u0441\u043a\u0432\u0430", "link": "https://hh.ru/vacancy/45562054?query=qa%20automation%20lead", "site": "https://hh.ru/search/vacancy"}, {"vacancy": "Head of QA / QA Lead / \u0420\u0443\u043a\u043e\u0432\u043e\u0434\u0438\u0442\u0435\u043b\u044c \u043e\u0442\u0434\u0435\u043b\u0430 \u0442\u0435\u0441\u0442\u0438\u0440\u043e\u0432\u0430\u043d\u0438\u044f", "min_salary": null, "max_salary": null, "currency": null, "company": "Occipital, Inc.", "city": "\u041c\u043e\u0441\u043a\u0432\u0430", "link": "https://hh.ru/vacancy/46047049?query=qa%20automation%20lead", "site": "https://hh.ru/search/vacancy"}, {"vacancy": "QA Automation Engineer (Java)", "min_salary": "160000", "max_salary": null, "currency": "\u0440\u0443\u0431", "company": "Amdocs", "city": "\u041c\u043e\u0441\u043a\u0432\u0430", "link": "https://hh.ru/vacancy/45724415?query=qa%20automation%20lead", "site": "https://hh.ru/search/vacancy"}, {"vacancy": "Middle QA Automation Engineer (Python)", "min_salary": "180000", "max_salary": "250000", "currency": "\u0440\u0443\u0431", "company": "Scalable Solutions", "city": "\u041c\u043e\u0441\u043a\u0432\u0430", "link": "https://hh.ru/vacancy/43394113?query=qa%20automation%20lead", "site": "https://hh.ru/search/vacancy"}, {"vacancy": "QA Lead", "min_salary": "3000", "max_salary": "3500", "currency": "USD", "company": "Alfacash", "city": "\u041c\u043e\u0441\u043a\u0432\u0430", "link": "https://hh.ru/vacancy/45293447?query=qa%20automation%20lead", "site": "https://hh.ru/search/vacancy"}, {"vacancy": "QA Automation Engineer (Senior or middle)", "min_salary": null, "max_salary": null, "currency": null, "company": "Bright Pattern, Inc", "city": "\u041c\u043e\u0441\u043a\u0432\u0430", "link": "https://hh.ru/vacancy/45784627?query=qa%20automation%20lead", "site": "https://hh.ru/search/vacancy"}, {"vacancy": "Lead QA (Automation)", "min_salary": null, "max_salary": null, "currency": null, "company": "Bitsgap Holding", "city": "\u041c\u043e\u0441\u043a\u0432\u0430", "link": "https://hh.ru/vacancy/45555206?query=qa%20automation%20lead", "site": "https://hh.ru/search/vacancy"}, {"vacancy": "Senior QA Automation Engineer / \u0422\u0435\u0441\u0442\u0438\u0440\u043e\u0432\u0449\u0438\u043a", "min_salary": "2000", "max_salary": "3500", "currency": "USD", "company": "Hostaway", "city": "\u041c\u043e\u0441\u043a\u0432\u0430", "link": "https://hh.ru/vacancy/45655368?query=qa%20automation%20lead", "site": "https://hh.ru/search/vacancy"}, {"vacancy": "Game QA Automation Lead", "min_salary": null, "max_salary": null, "currency": null, "company": "\u041e\u041e\u041e G5 Entertainment AB", "city": "\u041c\u043e\u0441\u043a\u0432\u0430", "link": "https://hh.ru/vacancy/46099586?query=qa%20automation%20lead", "site": "https://hh.ru/search/vacancy"}, {"vacancy": "Senior QA Automation Engineer", "min_salary": "200000", "max_salary": "250000", "currency": "\u0440\u0443\u0431", "company": "SIT Alemira", "city": "\u041c\u043e\u0441\u043a\u0432\u0430", "link": "https://hh.ru/vacancy/45114143?query=qa%20automation%20lead", "site": "https://hh.ru/search/vacancy"}, {"vacancy": "Senior QA Automation (Remote)", "min_salary": "3000", "max_salary": null, "currency": "USD", "company": "Affise Inc.", "city": "\u041c\u043e\u0441\u043a\u0432\u0430", "link": "https://hh.ru/vacancy/45987173?query=qa%20automation%20lead", "site": "https://hh.ru/search/vacancy"}, {"vacancy": "\u0412\u0435\u0434\u0443\u0449\u0438\u0439 \u0441\u043f\u0435\u0446\u0438\u0430\u043b\u0438\u0441\u0442 \u043f\u043e \u0430\u0432\u0442\u043e\u043c\u0430\u0442\u0438\u0437\u0438\u0440\u043e\u0432\u0430\u043d\u043d\u043e\u043c\u0443 \u0442\u0435\u0441\u0442\u0438\u0440\u043e\u0432\u0430\u043d\u0438\u044e / Automation QA", "min_salary": "250000", "max_salary": null, "currency": "\u0440\u0443\u0431", "company": "\u041f\u0410\u041e \u0414\u0435\u0442\u0441\u043a\u0438\u0439 \u041c\u0438\u0440", "city": "\u041c\u043e\u0441\u043a\u0432\u0430", "link": "https://hh.ru/vacancy/42116560?query=qa%20automation%20lead", "site": "https://hh.ru/search/vacancy"}, {"vacancy": "QA Automation Senior engineer - Payment Engines", "min_salary": null, "max_salary": null, "currency": null, "company": "Deutsche Bank Technology Center", "city": "\u041c\u043e\u0441\u043a\u0432\u0430", "link": "https://hh.ru/vacancy/45560678?query=qa%20automation%20lead", "site": "https://hh.ru/search/vacancy"}, {"vacancy": "\u0412\u0435\u0434\u0443\u0449\u0438\u0439 \u0438\u043d\u0436\u0435\u043d\u0435\u0440 \u043f\u043e \u0430\u0432\u0442\u043e\u043c\u0430\u0442\u0438\u0437\u0438\u0440\u043e\u0432\u0430\u043d\u043d\u043e\u043c\u0443 \u0442\u0435\u0441\u0442\u0438\u0440\u043e\u0432\u0430\u043d\u0438\u044e / Automated QA Engineer (Java/Kotlin)", "min_salary": null, "max_salary": null, "currency": null, "company": "WINLINE", "city": "\u041c\u043e\u0441\u043a\u0432\u0430", "link": "https://hh.ru/vacancy/46090839?query=qa%20automation%20lead", "site": "https://hh.ru/search/vacancy"}, {"vacancy": "Senior QA Automation engineer Java (\u043e\u043d\u043b\u0430\u0439\u043d \u043a\u0438\u043d\u043e\u0442\u0435\u0430\u0442\u0440 KION)", "min_salary": null, "max_salary": null, "currency": null, "company": "\u041f\u0410\u041e \u00ab\u041c\u0422\u0421\u00bb, IT", "city": "\u041c\u043e\u0441\u043a\u0432\u0430", "link": "https://hh.ru/vacancy/45405868?query=qa%20automation%20lead", "site": "https://hh.ru/search/vacancy"}, {"vacancy": "Senior QA engineer (java)", "min_salary": "300000", "max_salary": null, "currency": "\u0440\u0443\u0431", "company": "Kelly Services", "city": "\u041c\u043e\u0441\u043a\u0432\u0430", "link": "https://hh.ru/vacancy/46129821?query=qa%20automation%20lead", "site": "https://hh.ru/search/vacancy"}, {"vacancy": "QA automation engineer", "min_salary": null, "max_salary": null, "currency": null, "company": "\u04221 \u0418\u043d\u0442\u0435\u0433\u0440\u0430\u0446\u0438\u044f", "city": "\u041c\u043e\u0441\u043a\u0432\u0430", "link": "https://hh.ru/vacancy/44265501?query=qa%20automation%20lead", "site": "https://hh.ru/search/vacancy"}, {"vacancy": "Senior Automation QA", "min_salary": null, "max_salary": null, "currency": null, "company": "\u041e\u041e\u041e \u0418\u041a\u0421\u041f\u041b\u0410\u041d\u0415\u0422.\u0420\u0423", "city": "\u041c\u043e\u0441\u043a\u0432\u0430", "link": "https://hh.ru/vacancy/46006193?query=qa%20automation%20lead", "site": "https://hh.ru/search/vacancy"}, {"vacancy": "QA engineer", "min_salary": null, "max_salary": null, "currency": null, "company": "\u041e\u041e\u041e Gett", "city": "\u041c\u043e\u0441\u043a\u0432\u0430", "link": "https://hh.ru/vacancy/45084280?query=qa%20automation%20lead", "site": "https://hh.ru/search/vacancy"}, {"vacancy": "Automation QA Engineer", "min_salary": null, "max_salary": null, "currency": null, "company": "Uchi.ru", "city": "\u041c\u043e\u0441\u043a\u0432\u0430", "link": "https://hh.ru/vacancy/43856982?query=qa%20automation%20lead", "site": "https://hh.ru/search/vacancy"}, {"vacancy": "Senior QA Specialist", "min_salary": null, "max_salary": null, "currency": null, "company": "FLEETCOR \u0420\u043e\u0441\u0441\u0438\u044f", "city": "\u041c\u043e\u0441\u043a\u0432\u0430", "link": "https://hh.ru/vacancy/42951475?query=qa%20automation%20lead", "site": "https://hh.ru/search/vacancy"}, {"vacancy": "QA Automation (Java)", "min_salary": null, "max_salary": null, "currency": null, "company": "\u041e\u041e\u041e \u0410\u0440\u0435\u043d\u0430\u0434\u0430\u0442\u0430 \u0421\u043e\u0444\u0442\u0432\u0435\u0440", "city": "\u041c\u043e\u0441\u043a\u0432\u0430", "link": "https://hh.ru/vacancy/45905416?query=qa%20automation%20lead", "site": "https://hh.ru/search/vacancy"}, {"vacancy": "Python QA automation senior specialist", "min_salary": null, "max_salary": null, "currency": null, "company": "\u0421\u0431\u0435\u0440\u0417\u0432\u0443\u043a", "city": "\u041c\u043e\u0441\u043a\u0432\u0430", "link": "https://hh.ru/vacancy/39715839?query=qa%20automation%20lead", "site": "https://hh.ru/search/vacancy"}, {"vacancy": "Senior QA specialist - CurveEngine", "min_salary": null, "max_salary": null, "currency": null, "company": "Deutsche Bank Technology Center", "city": "\u041c\u043e\u0441\u043a\u0432\u0430", "link": "https://hh.ru/vacancy/45853311?query=qa%20automation%20lead", "site": "https://hh.ru/search/vacancy"}, {"vacancy": "QA Automation Engineer / \u0412\u0435\u0434\u0443\u0449\u0438\u0439 \u0441\u043f\u0435\u0446\u0438\u0430\u043b\u0438\u0441\u0442 \u0430\u0432\u0442\u043e\u0442\u0435\u0441\u0442\u0438\u0440\u043e\u0432\u0430\u043d\u0438\u044f", "min_salary": null, "max_salary": null, "currency": null, "company": "\u0412\u0441\u0435\u0433\u0434\u0430.\u0414\u0430", "city": "\u041c\u043e\u0441\u043a\u0432\u0430", "link": "https://hh.ru/vacancy/44935990?query=qa%20automation%20lead", "site": "https://hh.ru/search/vacancy"}, {"vacancy": "Senior/Middle automation Backend QA", "min_salary": "2300", "max_salary": null, "currency": "EUR", "company": "EXANTE", "city": "\u041c\u043e\u0441\u043a\u0432\u0430", "link": "https://hh.ru/vacancy/43501926?query=qa%20automation%20lead", "site": "https://hh.ru/search/vacancy"}, {"vacancy": "QA automation engineer", "min_salary": null, "max_salary": null, "currency": null, "company": "\u0421\u0431\u0435\u0440 \u0434\u043b\u044f \u044d\u043a\u0441\u043f\u0435\u0440\u0442\u043e\u0432", "city": "\u041c\u043e\u0441\u043a\u0432\u0430", "link": "https://hh.ru/vacancy/45932219?query=qa%20automation%20lead", "site": "https://hh.ru/search/vacancy"}, {"vacancy": "QA Automation Engineer", "min_salary": null, "max_salary": null, "currency": null, "company": "\u0410\u041e \u0420\u0422 \u041b\u0430\u0431\u0441", "city": "\u041c\u043e\u0441\u043a\u0432\u0430", "link": "https://hh.ru/vacancy/45641379?query=qa%20automation%20lead", "site": "https://hh.ru/search/vacancy"}, {"vacancy": "Senior QA Automation Engineer", "min_salary": "250000", "max_salary": null, "currency": "\u0440\u0443\u0431", "company": "Advantage Solutions", "city": "\u041c\u043e\u0441\u043a\u0432\u0430", "link": "https://hh.ru/vacancy/45909770?query=qa%20automation%20lead", "site": "https://hh.ru/search/vacancy"}, {"vacancy": "QA engineer - GTB Liquidity Deposits", "min_salary": null, "max_salary": null, "currency": null, "company": "Deutsche Bank Technology Center", "city": "\u041c\u043e\u0441\u043a\u0432\u0430", "link": "https://hh.ru/vacancy/45853382?query=qa%20automation%20lead", "site": "https://hh.ru/search/vacancy"}, {"vacancy": "QA Automation engineer", "min_salary": null, "max_salary": null, "currency": null, "company": "\u041e\u041e\u041e Accenture", "city": "\u041c\u043e\u0441\u043a\u0432\u0430", "link": "https://hh.ru/vacancy/42323946?query=qa%20automation%20lead", "site": "https://hh.ru/search/vacancy"}, {"vacancy": "\u0421\u0442\u0430\u0440\u0448\u0438\u0439 \u0438\u043d\u0436\u0435\u043d\u0435\u0440 \u043f\u043e \u0430\u0432\u0442\u043e\u043c\u0430\u0442\u0438\u0437\u0430\u0446\u0438\u0438 \u0438 \u0442\u0435\u0441\u0442\u0438\u0440\u043e\u0432\u0430\u043d\u0438\u044e / Senior QA Automation", "min_salary": null, "max_salary": null, "currency": null, "company": "\u0413\u041a \u041c\u0435\u0434\u0441\u0438. \u0423\u043f\u0440\u0430\u0432\u043b\u044f\u044e\u0449\u0430\u044f \u043a\u043e\u043c\u043f\u0430\u043d\u0438\u044f", "city": "\u041c\u043e\u0441\u043a\u0432\u0430", "link": "https://hh.ru/vacancy/45224786?query=qa%20automation%20lead", "site": "https://hh.ru/search/vacancy"}, {"vacancy": "Senior QA Engineer", "min_salary": null, "max_salary": null, "currency": null, "company": "\u041e\u041e\u041e \u0424\u0438\u043d\u0441\u0442\u0435\u043a \u0411\u0435\u043b", "city": "\u041c\u043e\u0441\u043a\u0432\u0430", "link": "https://hh.ru/vacancy/45890937?query=qa%20automation%20lead", "site": "https://hh.ru/search/vacancy"}, {"vacancy": "QA Automation Engineer", "min_salary": null, "max_salary": null, "currency": null, "company": "X5 RETAIL GROUP", "city": "\u041c\u043e\u0441\u043a\u0432\u0430", "link": "https://hh.ru/vacancy/41178269?query=qa%20automation%20lead", "site": "https://hh.ru/search/vacancy"}, {"vacancy": "SDET (Manual QA Engineer)", "min_salary": null, "max_salary": null, "currency": null, "company": "Parallels", "city": "\u041c\u043e\u0441\u043a\u0432\u0430", "link": "https://hh.ru/vacancy/42774630?query=qa%20automation%20lead", "site": "https://hh.ru/search/vacancy"}, {"vacancy": "PHP Senior QA Automation Engineer (\u0443\u0434\u0430\u043b\u0435\u043d\u043d\u043e)", "min_salary": "3500", "max_salary": null, "currency": "EUR", "company": "Wisebits", "city": "\u041c\u043e\u0441\u043a\u0432\u0430", "link": "https://hh.ru/vacancy/45160631?query=qa%20automation%20lead", "site": "https://hh.ru/search/vacancy"}, {"vacancy": "Senior QA automation engineer (JAVA)", "min_salary": null, "max_salary": null, "currency": null, "company": "\u041e\u041e\u041e \u0420\u0421\u0425\u0411-\u0418\u043d\u0442\u0435\u0445", "city": "\u041c\u043e\u0441\u043a\u0432\u0430", "link": "https://hh.ru/vacancy/44946313?query=qa%20automation%20lead", "site": "https://hh.ru/search/vacancy"}, {"vacancy": "Developer in Test / Senior QA Automation Engineer (Python)", "min_salary": null, "max_salary": null, "currency": null, "company": "GridGain Systems", "city": "\u041c\u043e\u0441\u043a\u0432\u0430", "link": "https://hh.ru/vacancy/45836932?query=qa%20automation%20lead", "site": "https://hh.ru/search/vacancy"}, {"vacancy": "Senior QA (auto)", "min_salary": null, "max_salary": null, "currency": null, "company": "SberTech", "city": "\u041c\u043e\u0441\u043a\u0432\u0430", "link": "https://hh.ru/vacancy/45743150?query=qa%20automation%20lead", "site": "https://hh.ru/search/vacancy"}, {"vacancy": "Middle/Senior QA Auto Engineer (Java/Selenium)", "min_salary": "250000", "max_salary": null, "currency": "\u0440\u0443\u0431", "company": "Selecty", "city": "\u041c\u043e\u0441\u043a\u0432\u0430", "link": "https://hh.ru/vacancy/45622214?query=qa%20automation%20lead", "site": "https://hh.ru/search/vacancy"}, {"vacancy": "Senior QA Engineer (with Automation)", "min_salary": "3500", "max_salary": "5200", "currency": "USD", "company": "IT_Selection", "city": "\u041c\u043e\u0441\u043a\u0432\u0430", "link": "https://hh.ru/vacancy/45533148?query=qa%20automation%20lead", "site": "https://hh.ru/search/vacancy"}, {"vacancy": "QA Automation \u0438\u043d\u0436\u0435\u043d\u0435\u0440", "min_salary": "200000", "max_salary": "330000", "currency": "\u0440\u0443\u0431", "company": "\u0418\u041f \u0428\u043f\u0430\u043a \u0412\u0438\u043a\u0442\u043e\u0440\u0438\u044f \u0421\u0435\u0440\u0433\u0435\u0435\u0432\u043d\u0430", "city": "\u041c\u043e\u0441\u043a\u0432\u0430", "link": "https://hh.ru/vacancy/44640465?query=qa%20automation%20lead", "site": "https://hh.ru/search/vacancy"}, {"vacancy": "QA Engineer (WebTeam)", "min_salary": "170000", "max_salary": null, "currency": "\u0440\u0443\u0431", "company": "JetBrains", "city": "\u041c\u043e\u0441\u043a\u0432\u0430", "link": "https://hh.ru/vacancy/43249770?query=qa%20automation%20lead", "site": "https://hh.ru/search/vacancy"}, {"vacancy": "QA Automation Engineer", "min_salary": null, "max_salary": null, "currency": null, "company": "WayRay", "city": "\u041c\u043e\u0441\u043a\u0432\u0430", "link": "https://hh.ru/vacancy/43883447?query=qa%20automation%20lead", "site": "https://hh.ru/search/vacancy"}, {"vacancy": "QA Automation (Java)", "min_salary": "200000", "max_salary": null, "currency": "\u0440\u0443\u0431", "company": "Bell Integrator", "city": "\u041c\u043e\u0441\u043a\u0432\u0430", "link": "https://hh.ru/vacancy/45573127?query=qa%20automation%20lead", "site": "https://hh.ru/search/vacancy"}, {"vacancy": "Senior QA Engineer (Citi Velocity)", "min_salary": null, "max_salary": null, "currency": null, "company": "\u0410\u041e Citibank", "city": "\u041c\u043e\u0441\u043a\u0432\u0430", "link": "https://hh.ru/vacancy/44356264?query=qa%20automation%20lead", "site": "https://hh.ru/search/vacancy"}, {"vacancy": "QA Automation Engineer", "min_salary": null, "max_salary": null, "currency": null, "company": "Marksman", "city": "\u041c\u043e\u0441\u043a\u0432\u0430", "link": "https://hh.ru/vacancy/45562231?query=qa%20automation%20lead", "site": "https://hh.ru/search/vacancy"}, {"vacancy": "Senior QA Engineer, MES", "min_salary": null, "max_salary": null, "currency": null, "company": "Align Technology", "city": "\u041c\u043e\u0441\u043a\u0432\u0430", "link": "https://hh.ru/vacancy/44042654?query=qa%20automation%20lead", "site": "https://hh.ru/search/vacancy"}, {"vacancy": "Senior QA Automation Engineer", "min_salary": null, "max_salary": null, "currency": null, "company": "\u0417\u0410\u041e 1\u0421", "city": "\u041c\u043e\u0441\u043a\u0432\u0430", "link": "https://hh.ru/vacancy/43680582?query=qa%20automation%20lead", "site": "https://hh.ru/search/vacancy"}, {"vacancy": "Senior QA Automation", "min_salary": null, "max_salary": null, "currency": null, "company": "\u041a\u043e\u043c\u043f\u0430\u043d\u0438\u044f \u00ab\u0421\u041f\u041e\u0420\u0422\u041c\u0410\u0421\u0422\u0415\u0420\u00bb, SM Lab", "city": "\u041c\u043e\u0441\u043a\u0432\u0430", "link": "https://hh.ru/vacancy/43911291?query=qa%20automation%20lead", "site": "https://hh.ru/search/vacancy"}, {"vacancy": "Senior QA Engineer", "min_salary": null, "max_salary": null, "currency": null, "company": "Miro", "city": "\u041c\u043e\u0441\u043a\u0432\u0430", "link": "https://hh.ru/vacancy/44897506?query=qa%20automation%20lead", "site": "https://hh.ru/search/vacancy"}, {"vacancy": "QA automation engineer", "min_salary": null, "max_salary": null, "currency": null, "company": "\u041e\u041e\u041e \u042e\u043d\u0438\u0442\u0430\u0440\u0438\u0443\u0441", "city": "\u041c\u043e\u0441\u043a\u0432\u0430", "link": "https://hh.ru/vacancy/43791718?query=qa%20automation%20lead", "site": "https://hh.ru/search/vacancy"}, {"vacancy": "QA automation \u0438\u043d\u0436\u0435\u043d\u0435\u0440 (\u043d\u0430\u0433\u0440\u0443\u0437\u043e\u0447\u043d\u043e\u0435 \u0442\u0435\u0441\u0442\u0438\u0440\u043e\u0432\u0430\u043d\u0438\u0435)", "min_salary": null, "max_salary": null, "currency": null, "company": "Hi, Rockits!", "city": "\u041c\u043e\u0441\u043a\u0432\u0430", "link": "https://hh.ru/vacancy/45539696?query=qa%20automation%20lead", "site": "https://hh.ru/search/vacancy"}, {"vacancy": "QA Automation Engineer (\u0414\u041a\u041e)", "min_salary": null, "max_salary": null, "currency": null, "company": "\u04221 \u041a\u043e\u043d\u0441\u0430\u043b\u0442\u0438\u043d\u0433", "city": "\u041c\u043e\u0441\u043a\u0432\u0430", "link": "https://hh.ru/vacancy/43531678?query=qa%20automation%20lead", "site": "https://hh.ru/search/vacancy"}, {"vacancy": "Senior QA Engineer / QA Lead", "min_salary": null, "max_salary": null, "currency": null, "company": "Ventra", "city": "\u041c\u043e\u0441\u043a\u0432\u0430", "link": "https://hh.ru/vacancy/45562152?query=qa%20automation%20lead", "site": "https://hh.ru/search/vacancy"}, {"vacancy": "Senior/Middle QA Automation", "min_salary": null, "max_salary": null, "currency": null, "company": "\u041a\u043e\u043c\u043f\u0430\u043d\u0438\u044f \u00ab\u0421\u041f\u041e\u0420\u0422\u041c\u0410\u0421\u0422\u0415\u0420\u00bb, SM Lab", "city": "\u041c\u043e\u0441\u043a\u0432\u0430", "link": "https://hh.ru/vacancy/42707053?query=qa%20automation%20lead", "site": "https://hh.ru/search/vacancy"}]